keygen/__init__.py
python_keygen-1.6.dist-info/LICENCE
python_keygen-1.6.dist-info/METADATA
python_keygen-1.6.dist-info/WHEEL
python_keygen-1.6.dist-info/top_level.txt
python_keygen-1.6.dist-info/RECORD
