Metadata-Version: 2.1
Name: python-keygen
Version: 1.6
Summary: Key-Generator With Validator Written in Python
Home-page: https://github.com/pmk456/keygen
Author: Patan Musthakheem
Author-email: patanmusthakheem786@gmail.com
License: UNKNOWN
Project-URL: Bug Tracker, https://github.com/pmk456/keygen/issues
Platform: UNKNOWN
Classifier: Programming Language :: Python :: 3
Classifier: License :: OSI Approved :: Apache Software License
Classifier: Operating System :: OS Independent
Requires-Python: >=3.6
License-File: LICENCE
